tidynotes/__init__.py
tidynotes/__main__.py
tidynotes/logs.py
tidynotes/mardown_document.py
tidynotes/notebook.py
tidynotes/__pycache__/__init__.cpython-36.pyc
tidynotes/__pycache__/__init__.cpython-37.pyc
tidynotes/__pycache__/__init__.cpython-38.pyc
tidynotes/__pycache__/__main__.cpython-36.pyc
tidynotes/__pycache__/__main__.cpython-37.pyc
tidynotes/__pycache__/logs.cpython-36.pyc
tidynotes/__pycache__/logs.cpython-38.pyc
tidynotes/__pycache__/mardown_document.cpython-36.pyc
tidynotes/__pycache__/notebook.cpython-36.pyc
tidynotes/__pycache__/notebook.cpython-37.pyc
tidynotes/__pycache__/notebook.cpython-38.pyc
tidynotes/__pycache__/render_engine.cpython-38.pyc
tidynotes/templates/config.json
tidynotes/templates/corrections.json
tidynotes/templates/document.html
tidynotes/templates/note.css
tidynotes/templates/note.md
tidynotes/templates/page.html
tidynotes/templates/render_changes.json
tidynotes-21.1.1.dist-info/LICENSE
tidynotes-21.1.1.dist-info/METADATA
tidynotes-21.1.1.dist-info/WHEEL
tidynotes-21.1.1.dist-info/entry_points.txt
tidynotes-21.1.1.dist-info/top_level.txt
tidynotes-21.1.1.dist-info/RECORD
