Metadata-Version: 2.1
Name: tidynotes
Version: 21.1.1
Summary: A simple digital notebook using Markdown.
Home-page: https://github.com/JosephMcGrath/tidynotes
Author: Joe McGrath
License: MIT
Platform: UNKNOWN
Classifier: License :: OSI Approved :: MIT License
Classifier: Programming Language :: Python :: 3
Classifier: Programming Language :: Python :: 3.6
Classifier: Programming Language :: Python :: 3.7
Classifier: Programming Language :: Python :: 3.8
Classifier: Natural Language :: English
Classifier: Operating System :: Microsoft :: Windows
Classifier: Operating System :: Microsoft :: Windows :: Windows 10
Classifier: Topic :: Office/Business :: News/Diary
Requires-Dist: jinja2
Requires-Dist: markdown
Requires-Dist: pyyaml
